LICENSE
README.md
setup.json
setup.py
aiida_catmat/__init__.py
aiida_catmat.egg-info/PKG-INFO
aiida_catmat.egg-info/SOURCES.txt
aiida_catmat.egg-info/dependency_links.txt
aiida_catmat.egg-info/entry_points.txt
aiida_catmat.egg-info/requires.txt
aiida_catmat.egg-info/top_level.txt
aiida_catmat/calcfunctions/__init__.py
aiida_catmat/calcfunctions/other.py
aiida_catmat/parsers/__init__.py
aiida_catmat/utils/__init__.py
aiida_catmat/utils/mapping.py
aiida_catmat/workchains/__init__.py
aiida_catmat/workchains/base.py
aiida_catmat/workchains/vasp_catmat.py
aiida_catmat/workchains/vasp_converge.py
aiida_catmat/workchains/vasp_multistage.py
aiida_catmat/workchains/vasp_multistage_ddec.py