Metadata-Version: 2.1
Name: aiida-catmat
Version: 1.0.0b0
Summary: Collection of AiiDA WorkChains Developed in Morgan Group
Home-page: https://github.com/pzarabadip/aiida-catmat
Author: Pezhman Zarabadi-Poor
Author-email: pzarabadip@gmail.com
License: MIT License
Classifier: Programming Language :: Python :: 3.8
Classifier: Programming Language :: Python :: 3.9
Provides-Extra: testing
Provides-Extra: pre-commit
Provides-Extra: docs
License-File: LICENSE
